criar_automacoes/__init__.py
criar_automacoes/criar_automacoes.py
criar_automacoes-0.1.6.dist-info/METADATA
criar_automacoes-0.1.6.dist-info/WHEEL
criar_automacoes-0.1.6.dist-info/RECORD
